{
  "basics": {
    "name": "Laila Abella",
    "label": "TA",
    "picture": "https://Lailaaa.github.io/images/Lailaaa.JPG",
    "email": "abellal@hawaii.edu",
    "phone": "",
    "website": "https://Lailaaa.github.io",
    "summary": "I am studying for a B.B.A. in Finance and Managment Information Systems at the University of Hawaii. I expect to graduate in Spring, 2020.",
    "location": {
      "address": "",
      "postalCode": "96822",
      "city": "Honolulu",
      "countryCode": "USA",
      "region": "Hawaii"
    },
    "profiles": [
      {
        "network": "github",
        "username": "Lailaaa",
        "url": "http://github.com/Lailaaa"
      }
    ]
  },
  "interests": [
    {
      "name": "Numbers",
      "keywords": [
      ]
    },
    {
      "name": "Coding",
      "keywords": [
      ]
    },
    {
      "name": "Music",
      "keywords": [
      ]
    },
    {
      "name": "Traveling",
      "keywords": [
      ]
    }
  ],
  "skills": [
    {
      "name": "Languages and Frameworks",
      "level": "",
      "keywords": [
        "C",
        "C++",
        "Java",
        "Javascript",
        "Assembly",
        "Common Lisp"
      ]
    },
    {
      "name": "Toolsets/OS",
      "level": "",
      "keywords": [
        "MacOS",
        "Ubuntu",
        "Git/GitHub",
        "g++",
        "TI LaunchPad"
      ]
    }
  ],
  "education": [
    {
      "institution": "University of Hawaii, Honolulu, HI",
      "area": "Finance and MIS (expected Spring, 2020)",
      "studyType": "B.B.A.",
      "startDate": "2016-08-24",
      "endDate": "Present",
      "gpa": "",
      "courses": [
      ]
    }
  ],
  "work": [
    {
      "company": "UH Manoa Shidler College of Business",
      "position": "TA/Grader for BUS 311 and ITM 352",
      "website": "",
      "startDate": "2019-09-23",
      "endDate": "Present",
      "summary": "Help students and grade assignments from both BUS 311 and ITM 352",
      "highlights": [
        "Maintain, update, and oversee Laulima",
        "Grade assignments"
      ]
    }
  ],
  "awards": [
    {
      "title": "B+ Scholarship",
      "date": "2016-Present",
      "awarder": "State of Hawaii",
      "summary": "Scholarships awarded to incoming freshmen and continuing students who complete a rigorous high school curriculum with a minimum overall GPA of 3.0 at a Hawai'i public school."
    },
    {
      "title": "Dean's List",
      "date": "2016-Present",
      "awarder": "University of Hawaii Dean",
      "summary": "Students will be awarded Dean's List Honors for a semester in which they complete a minimum of 12 graded credits with a grade point average of 3.50 or better."
    }
  ],
  "references": [
    {
      "name": "Available upon request",
      "reference": ""
    }
  ]
}
